MANIFEST.in
changes.txt
license.txt
readme.md
setup.py
nive_markdowntext/__init__.py
nive_markdowntext/mtext.pt
nive_markdowntext/mtext.py
nive_markdowntext/tests.py
nive_markdowntext.egg-info/PKG-INFO
nive_markdowntext.egg-info/SOURCES.txt
nive_markdowntext.egg-info/dependency_links.txt
nive_markdowntext.egg-info/not-zip-safe
nive_markdowntext.egg-info/requires.txt
nive_markdowntext.egg-info/top_level.txt