Metadata-Version: 1.1
Name: nive-markdowntext
Version: 0.1.2
Summary: Markdown text element for Nive cms
Home-page: http://cms.nive.co
Author: Arndt Droullier, Nive GmbH
Author-email: info@nive.co
License: GPL 3
Keywords: markdown cms website publisher pyramid
Platform: UNKNOWN
Classifier: Intended Audience :: Developers
Classifier: Programming Language :: Python
Classifier: Framework :: Pyramid
Classifier: License :: OSI Approved :: GNU General Public License v3 (GPLv3)
Classifier: Development Status :: 4 - Beta
Classifier: Programming Language :: Python :: 2.6
Classifier: Programming Language :: Python :: 2.7
